Metadata-Version: 2.4
Name: FlcatDrissionPage
Version: 0.1.33
Summary: Python based web automation tool. It can control the browser and send and receive data packets.
Author-email: yhhit <827077539@qq.com>
Keywords: FlcatDrissionPage
Classifier: Programming Language :: Python :: 3.9
Classifier: Development Status :: 4 - Beta
Classifier: Topic :: Utilities
Requires-Python: >=3.9
License-File: LICENSE
Requires-Dist: lxml
Requires-Dist: requests
Requires-Dist: cssselect
Requires-Dist: DownloadKit>=2.0.7
Requires-Dist: websocket-client
Requires-Dist: click
Requires-Dist: tldextract>=3.4.4
Requires-Dist: psutil
Requires-Dist: loguru
Dynamic: license-file
